data_utils/__init__.py
data_utils/higher_order_functions.py
data_utils/higher_order_functions_test.py
data_utils/safe_coerce.py
data_utils/safe_coerce_test.py
data_utils-0.0.7.dist-info/METADATA
data_utils-0.0.7.dist-info/RECORD
data_utils-0.0.7.dist-info/WHEEL
data_utils-0.0.7.dist-info/top_level.txt
src/__init__.py
src/higher_order_functions.py
src/higher_order_functions_test.py
src/safe_coerce.py
src/safe_coerce_test.py
