Metadata-Version: 2.1
Name: data-utils
Version: 0.0.7
Summary: An assortment of utilities for handling dirty, dirty data.
Home-page: https://github.com/raywhite/data-utils
Author: axdg
Author-email: axdg@dfant.asia
License: UNLICENSED
Keywords: hof higher-order data utilities
Platform: UNKNOWN
Requires-Python: >=2.6,<=3.0
Requires-Dist: phonenumberslite
